pov_fabric.py
pov_fabric_helpers-0.3.dist-info/DESCRIPTION.rst
pov_fabric_helpers-0.3.dist-info/METADATA
pov_fabric_helpers-0.3.dist-info/RECORD
pov_fabric_helpers-0.3.dist-info/WHEEL
pov_fabric_helpers-0.3.dist-info/metadata.json
pov_fabric_helpers-0.3.dist-info/pbr.json
pov_fabric_helpers-0.3.dist-info/top_level.txt
