Metadata-Version: 2.0
Name: pov-fabric-helpers
Version: 0.3
Summary: Fabric helpers we use at PoV
Home-page: https://github.com/ProgrammersOfVilnius/pov-fabric-helpers/
Author: Marius Gedminas
Author-email: marius@pov.lt
License: MIT
Platform: UNKNOWN
Classifier: Development Status :: 4 - Beta
Classifier: License :: OSI Approved :: MIT License
Requires-Dist: Fabric
